newpreProcessingGEP/__init__.py
newpreProcessingGEP-1.0.7.dist-info/LICENSE
newpreProcessingGEP-1.0.7.dist-info/METADATA
newpreProcessingGEP-1.0.7.dist-info/WHEEL
newpreProcessingGEP-1.0.7.dist-info/top_level.txt
newpreProcessingGEP-1.0.7.dist-info/RECORD
