Metadata-Version: 2.1
Name: newpreProcessingGEP
Version: 1.0.7
Summary: A package for preprocessing text
Home-page: https://github.com/vanshajsingla03/newpreProcessingGEP
Author: Vanshaj Singla
Author-email: vanshaj.singla@gep.com
Classifier: Programming Language :: Python :: 3
Classifier: License :: OSI Approved :: MIT License
Classifier: Operating System :: OS Independent
Requires-Python: >=3.6
License-File: LICENSE
